spinesUtils/__init__.py
spinesUtils/decorators.py
spinesUtils/logging.py
spinesUtils/timer.py
spinesUtils/asserts/__init__.py
spinesUtils/asserts/_func_params.py
spinesUtils/asserts/_inspect.py
spinesUtils/asserts/_type_and_exceptions.py
spinesUtils/asserts/test_assert_performance.py
spinesUtils/data_insight/__init__.py
spinesUtils/data_insight/_df_preview.py
spinesUtils/feature_tools/__init__.py
spinesUtils/feature_tools/_feature_tools.py
spinesUtils/io/__init__.py
spinesUtils/io/_data.py
spinesUtils/models/__init__.py
spinesUtils/models/imbalanced_classifier.py
spinesUtils/preprocessing/__init__.py
spinesUtils/preprocessing/_compress_memory.py
spinesUtils/preprocessing/_split_tools.py
spinesUtils/utils/__init__.py
spinesUtils/utils/_utils.py
spinesutils-0.5.0.dist-info/LICENSE
spinesutils-0.5.0.dist-info/METADATA
spinesutils-0.5.0.dist-info/WHEEL
spinesutils-0.5.0.dist-info/top_level.txt
spinesutils-0.5.0.dist-info/RECORD
