Metadata-Version: 2.2
Name: spinesUtils
Version: 0.5.0
Summary: spinesUtils is a user-friendly toolkit for python development.
Home-page: https://github.com/BirchKwok/spinesUtils
Author: Birch Kwok
Author-email: birchkwok@gmail.com
License: Apache 2.0
Keywords: Helpful tools for python development
Classifier: License :: OSI Approved :: Apache Software License
Classifier: Operating System :: OS Independent
Classifier: Programming Language :: Python :: 3.9
Classifier: Programming Language :: Python :: 3.10
Classifier: Programming Language :: Python :: 3.11
Classifier: Programming Language :: Python :: 3.12
Classifier: Programming Language :: Python :: 3.13
License-File: LICENSE
Requires-Dist: pytz>=2021.1
Requires-Dist: pydantic>=2.5.2
Requires-Dist: atexit>=0.1.1
Provides-Extra: all
Requires-Dist: scikit-learn>=1.0.2; extra == "all"
Requires-Dist: numpy>=1.17.0; extra == "all"
Requires-Dist: pandas>=2.0.0; extra == "all"
Requires-Dist: tqdm>=4.65.0; extra == "all"
Requires-Dist: dask>=2023.6.0; extra == "all"
Requires-Dist: pyarrow>=14.0.1; extra == "all"
Requires-Dist: polars>=0.19.3; extra == "all"
Requires-Dist: pytz>=2021.1; extra == "all"
Requires-Dist: numba>=0.58.1; extra == "all"
Dynamic: author
Dynamic: author-email
Dynamic: classifier
Dynamic: description
Dynamic: description-content-type
Dynamic: home-page
Dynamic: keywords
Dynamic: license
Dynamic: provides-extra
Dynamic: requires-dist
Dynamic: summary
